el_pagination/__init__.py
el_pagination/decorators.py
el_pagination/exceptions.py
el_pagination/loaders.py
el_pagination/models.py
el_pagination/paginators.py
el_pagination/settings.py
el_pagination/utils.py
el_pagination/views.py
el_pagination/locale/de/LC_MESSAGES/django.mo
el_pagination/locale/de/LC_MESSAGES/django.po
el_pagination/locale/es/LC_MESSAGES/django.mo
el_pagination/locale/es/LC_MESSAGES/django.po
el_pagination/locale/fr/LC_MESSAGES/django.mo
el_pagination/locale/fr/LC_MESSAGES/django.po
el_pagination/locale/it/LC_MESSAGES/django.mo
el_pagination/locale/it/LC_MESSAGES/django.po
el_pagination/locale/pt_BR/LC_MESSAGES/django.mo
el_pagination/locale/pt_BR/LC_MESSAGES/django.po
el_pagination/locale/zh_CN/LC_MESSAGES/django.mo
el_pagination/locale/zh_CN/LC_MESSAGES/django.po
el_pagination/static/el-pagination/js/el-pagination.js
el_pagination/templates/el_pagination/current_link.html
el_pagination/templates/el_pagination/next_link.html
el_pagination/templates/el_pagination/page_link.html
el_pagination/templates/el_pagination/previous_link.html
el_pagination/templates/el_pagination/show_more.html
el_pagination/templates/el_pagination/show_more_table.html
el_pagination/templates/el_pagination/show_pages.html
el_pagination/templatetags/__init__.py
el_pagination/templatetags/el_pagination_tags.py
django_el_pagination-4.1.2.dist-info/LICENSE
django_el_pagination-4.1.2.dist-info/METADATA
django_el_pagination-4.1.2.dist-info/WHEEL
django_el_pagination-4.1.2.dist-info/top_level.txt
django_el_pagination-4.1.2.dist-info/RECORD
