Metadata-Version: 2.1
Name: django-el-pagination
Version: 4.1.2
Summary: Django pagination tools supporting Ajax, multiple and lazy pagination, Twitter-style and Digg-style pagination.
Author: Francesco Banconi
Author-email: Oleksandr Shtalinberg <O.Shtalinberg@gmail.com>
License: Copyright (c) 2009-2013 Francesco Banconi
Project-URL: Homepage, http://github.com/shtalinberg/django-el-pagination
Project-URL: Documentation, http://django-el-pagination.readthedocs.org/
Project-URL: Repository, https://github.com/shtalinberg/django-el-pagination.git
Project-URL: Bug Tracker, https://github.com/shtalinberg/django-el-pagination/issues
Keywords: django,pagination,ajax,endless
Classifier: Development Status :: 5 - Production/Stable
Classifier: Environment :: Web Environment
Classifier: Framework :: Django
Classifier: Framework :: Django :: 3.2
Classifier: Framework :: Django :: 4.2
Classifier: Framework :: Django :: 5.0
Classifier: Intended Audience :: Developers
Classifier: License :: OSI Approved :: MIT License
Classifier: Operating System :: OS Independent
Classifier: Programming Language :: Python
Classifier: Programming Language :: Python :: 3
Classifier: Programming Language :: Python :: 3.8
Classifier: Programming Language :: Python :: 3.9
Classifier: Programming Language :: Python :: 3.10
Classifier: Programming Language :: Python :: 3.11
Classifier: Programming Language :: Python :: 3.12
Classifier: Topic :: Utilities
Requires-Python: >=3.8
License-File: LICENSE
Requires-Dist: django>=3.2.0
